yowsup_gateway/__init__.py
yowsup_gateway/exceptions.py
yowsup_gateway/layer.py
yowsup_gateway/results.py
yowsup_gateway/stack.py
yowsup_gateway-0.1.1.dist-info/DESCRIPTION.rst
yowsup_gateway-0.1.1.dist-info/METADATA
yowsup_gateway-0.1.1.dist-info/RECORD
yowsup_gateway-0.1.1.dist-info/WHEEL
yowsup_gateway-0.1.1.dist-info/metadata.json
yowsup_gateway-0.1.1.dist-info/top_level.txt
