Metadata-Version: 2.0
Name: yowsup-gateway
Version: 0.1.1
Summary: Yowsup Gateway pretends to be a link between yowsup library and client applications
Home-page: https://github.com/jlmadurga/yowsup-gateway
Author: Juan Madurga
Author-email: jlmadurga@gmail.com
License: ISCL
Keywords: yowsup-gateway
Platform: UNKNOWN
Classifier: Development Status :: 2 - Pre-Alpha
Classifier: Intended Audience :: Developers
Classifier: License :: OSI Approved :: ISC License (ISCL)
Classifier: Natural Language :: English
Classifier: Programming Language :: Python :: 2
Classifier: Programming Language :: Python :: 2.6
Classifier: Programming Language :: Python :: 2.7
Classifier: Programming Language :: Python :: 3
Classifier: Programming Language :: Python :: 3.3
Classifier: Programming Language :: Python :: 3.4
Requires-Dist: yowsup2
